ugen/__init__.py
ugen-0.1.0.dist-info/METADATA
ugen-0.1.0.dist-info/WHEEL
ugen-0.1.0.dist-info/top_level.txt
ugen-0.1.0.dist-info/RECORD
