Metadata-Version: 2.1
Name: ugen
Version: 0.1.0
Summary: More powerful than pytorch
Home-page: https://github.com/ugen/ugen
Author: Yougen
Author-email: you@gen.com
License: UNKNOWN
Platform: UNKNOWN
Classifier: Programming Language :: Python :: 3
Classifier: License :: OSI Approved :: MIT License
Classifier: Operating System :: OS Independent
Requires-Python: >=3.6
Requires-Dist: torch
